WebpackZhongwenZhinan/README.md
WebpackZhongwenZhinan/__init__.py
WebpackZhongwenZhinan/__main__.py
WebpackZhongwenZhinan/file.epub
WebpackZhongwenZhinan/index.html
WebpackZhongwenZhinan/css/__init__.py
WebpackZhongwenZhinan/css/annotations.css
WebpackZhongwenZhinan/css/main.css
WebpackZhongwenZhinan/css/normalize.css
WebpackZhongwenZhinan/css/popup.css
WebpackZhongwenZhinan/font/__init__.py
WebpackZhongwenZhinan/font/fontello.eot
WebpackZhongwenZhinan/font/fontello.svg
WebpackZhongwenZhinan/font/fontello.ttf
WebpackZhongwenZhinan/font/fontello.woff
WebpackZhongwenZhinan/img/__init__.py
WebpackZhongwenZhinan/img/annotator-glyph-sprite.png
WebpackZhongwenZhinan/img/annotator-icon-sprite.png
WebpackZhongwenZhinan/img/apple-touch-icon.png
WebpackZhongwenZhinan/img/cancelfullscreen.png
WebpackZhongwenZhinan/img/close.png
WebpackZhongwenZhinan/img/fullscreen.png
WebpackZhongwenZhinan/img/loader.gif
WebpackZhongwenZhinan/img/menu-icon.png
WebpackZhongwenZhinan/img/save.png
WebpackZhongwenZhinan/img/saved.png
WebpackZhongwenZhinan/img/settings-s.png
WebpackZhongwenZhinan/img/settings.png
WebpackZhongwenZhinan/img/star.png
WebpackZhongwenZhinan/js/__init__.py
WebpackZhongwenZhinan/js/epub.js
WebpackZhongwenZhinan/js/epub.min.js
WebpackZhongwenZhinan/js/epub.min.map
WebpackZhongwenZhinan/js/hooks.min.js
WebpackZhongwenZhinan/js/hooks.min.map
WebpackZhongwenZhinan/js/reader.js
WebpackZhongwenZhinan/js/reader.js.map
WebpackZhongwenZhinan/js/reader.min.js
WebpackZhongwenZhinan/js/reader.min.map
WebpackZhongwenZhinan/js/hooks/__init__.py
WebpackZhongwenZhinan/js/hooks/extensions/__init__.py
WebpackZhongwenZhinan/js/hooks/extensions/highlight.js
WebpackZhongwenZhinan/js/libs/__init__.py
WebpackZhongwenZhinan/js/libs/jquery.min.js
WebpackZhongwenZhinan/js/libs/localforage.min.js
WebpackZhongwenZhinan/js/libs/screenfull.js
WebpackZhongwenZhinan/js/libs/screenfull.min.js
WebpackZhongwenZhinan/js/libs/zip.min.js
WebpackZhongwenZhinan/js/plugins/__init__.py
webpack_zhongwen_zhinan-2024.3.4.0.dist-info/METADATA
webpack_zhongwen_zhinan-2024.3.4.0.dist-info/WHEEL
webpack_zhongwen_zhinan-2024.3.4.0.dist-info/entry_points.txt
webpack_zhongwen_zhinan-2024.3.4.0.dist-info/top_level.txt
webpack_zhongwen_zhinan-2024.3.4.0.dist-info/RECORD
